G09/clock.v
/* Aluno: Henrique Augusto Rodrigues
* Matricula: 675263
* Arquitetura 1 - Tarde
* Guia_09  Exemplo 0901.
*/

/*
* Clock Generator
*/
module clock (output clk);
reg clk;

initial
  begin
    clk = 1'b0;
  end

always
  begin
    #12 clk = ~clk;
end
endmodule
/*
module main;

wire clk;
clock CLK1 (clk);

initial begin
$dumpfile("Exemplo_0901.vcd");
$dumpvars;

#120 $finish;
end
endmodule
*/

G09/Exemplo_0907.v
/* Aluno: Henrique Augusto Rodrigues
* Matricula: 675263
* Arquitetura 1 - Tarde
* Guia_09  Exemplo 0907.
*/

//inclusoes
`include "clock.v"

/*
*modulos
*/

module pulse (signal, clock);
input clock;
output signal;
reg signal;

always @ ( negedge clock)
begin
  signal = 1'b1;
#3 signal = 1'b0;
/*
#3 signal = 1'b1;
#3 signal = 1'b0;
#3 signal = 1'b1;
#3 signal = 1'b0;
#3 signal = 1'b1;
#3 signal = 1'b0;
*/
end
endmodule

module main;

clock clk(clock);
wire p;

pulse pls (p, clock);


initial begin
$dumpfile("Exemplo_0907.vcd");
$dumpvars(1, clock, p);

#480 $finish;

end
endmodule

G09/Exemplo_0904a.vcd
$date
	Mon Sept 28 15:43:20 2020
$end
$version
	Icarus Verilog
$end
$timescale
	1s
$end
$scope module main $end
$var wire 1 ! clock $end
$upscope $end
$scope module main $end
$var wire 1 " p $end
$upscope $end
$enddefinitions $end
#0
$dumpvars
x"
0!
$end
#12
1"
1!
#24
0!
#36
1!
0"
#48
0!
#60
1!
1"
#72
0!
#84
1!
0"
#96
0!
#108
1!
1"
#120
0!
#132
1!
0"
#144
0!
#156
1!
1"
#168
0!
#180
1!
0"
#192
0!
#204
1!
1"
#216
0!
#228
1!
0"
#240
0!
#252
1!
1"
#264
0!
#276
1!
0"
#288
0!
#300
1!
1"
#312
0!
#324
1!
0"
#336
0!
#348
1!
1"
#360
0!
#372
1!
0"
#384
0!
#396
1!
1"
#408
0!
#420
1!
0"
#432
0!
#444
1!
1"
#456
0!
#468
1!
0"
