G09/clock.v
/* Aluno: Henrique Augusto Rodrigues
* Matricula: 675263
* Arquitetura 1 - Tarde
* Guia_09  Exemplo 0901.
*/

/*
* Clock Generator
*/
module clock (output clk);
reg clk;

initial
  begin
    clk = 1'b0;
  end

always
  begin
    #12 clk = ~clk;
end
endmodule
/*
module main;

wire clk;
clock CLK1 (clk);

initial begin
$dumpfile("Exemplo_0901.vcd");
$dumpvars;

#120 $finish;
end
endmodule
*/

G09/Exemplo_0907.v
/* Aluno: Henrique Augusto Rodrigues
* Matricula: 675263
* Arquitetura 1 - Tarde
* Guia_09  Exemplo 0907.
*/

//inclusoes
`include "clock.v"

/*
*modulos
*/

module pulse (signal, clock);
input clock;
output signal;
reg signal;

always @ ( negedge clock)
begin
  signal = 1'b1;
#3 signal = 1'b0;
/*
#3 signal = 1'b1;
#3 signal = 1'b0;
#3 signal = 1'b1;
#3 signal = 1'b0;
#3 signal = 1'b1;
#3 signal = 1'b0;
*/
end
endmodule

module main;

clock clk(clock);
wire p;

pulse pls (p, clock);


initial begin
$dumpfile("Exemplo_0907.vcd");
$dumpvars(1, clock, p);

#480 $finish;

end
endmodule

G09/Exemplo_0906a.vcd
$date
	Mon Sept 28 20:11:17 2020
$end
$version
	Icarus Verilog
$end
$timescale
	1s
$end
$scope module main $end
$var wire 1 ! clock $end
$upscope $end
$scope module main $end
$var wire 1 " p $end
$upscope $end
$enddefinitions $end
#0
$dumpvars
x"
0!
$end
#12
1"
1!
#14
0"
#24
0!
#36
1"
1!
#38
0"
#48
0!
#60
1"
1!
#62
0"
#72
0!
#84
1"
1!
#86
0"
#96
0!
#108
1"
1!
#110
0"
#120
0!
#132
1"
1!
#134
0"
#144
0!
#156
1"
1!
#158
0"
#168
0!
#180
1"
1!
#182
0"
#192
0!
#204
1"
1!
#206
0"
#216
0!
#228
1"
1!
#230
0"
#240
0!
#252
1"
1!
#254
0"
#264
0!
#276
1"
1!
#278
0"
#288
0!
#300
1"
1!
#302
0"
#312
0!
#324
1"
1!
#326
0"
#336
0!
#348
1"
1!
#350
0"
#360
0!
#372
1"
1!
#374
0"
#384
0!
#396
1"
1!
#398
0"
#408
0!
#420
1"
1!
#422
0"
#432
0!
#444
1"
1!
#446
0"
#456
0!
#468
1"
1!
#470
0"
